ezcoo_cli/__init__.py
ezcoo_cli/cli.py
ezcoo_cli/device.py
ezcoo_cli/kvm.py
ezcoo_cli/models.py
ezcoo_cli-0.2.0.dist-info/METADATA
ezcoo_cli-0.2.0.dist-info/WHEEL
ezcoo_cli-0.2.0.dist-info/entry_points.txt
ezcoo_cli-0.2.0.dist-info/licenses/LICENSE
ezcoo_cli-0.2.0.dist-info/RECORD
