Metadata-Version: 2.4
Name: ezcoo-cli
Version: 0.2.0
Summary: A tool to control EZCOO KVM switches via the serial interface
Author-email: Simon Brakhane <simon@brakhane.net>
License-Expression: GPL-3.0-or-later
License-File: LICENSE
Requires-Python: >=3.10
Requires-Dist: click>=8.1.3
Requires-Dist: pyserial>=3.5
